{
  "source": "goonhammer",
  "url": "https://www.goonhammer.com/how-to-paint-everything-conquest-sorcerer-kings-part-1/",
  "title": "How To Paint Everything: Conquest Sorcerer Kings Part 1",
  "paints": [
    {
      "brand": "Citadel",
      "name": "Contrast",
      "confidence": 0.9
    },
    {
      "brand": "Citadel",
      "name": "Space Wolves Grey",
      "confidence": 0.9
    },
    {
      "brand": "Citadel",
      "name": "Russ Grey",
      "confidence": 0.9
    },
    {
      "brand": "Citadel",
      "name": "Fenrisian Grey",
      "confidence": 0.9
    },
    {
      "brand": "Citadel",
      "name": "Black Templar",
      "confidence": 0.9
    },
    {
      "brand": "Citadel",
      "name": "Nuln",
      "confidence": 0.9
    },
    {
      "brand": "Citadel",
      "name": "Thousand Sons Blue",
      "confidence": 0.9
    },
    {
      "brand": "Citadel",
      "name": "Gore-Grunta",
      "confidence": 0.9
    },
    {
      "brand": "Citadel",
      "name": "Guilliman Flesh",
      "confidence": 0.9
    },
    {
      "brand": "Citadel",
      "name": "Skeleton Horde Contrast",
      "confidence": 0.9
    },
    {
      "brand": "Citadel",
      "name": "Ushabti",
      "confidence": 0.9
    },
    {
      "brand": "Citadel",
      "name": "Screaming Skull",
      "confidence": 0.9
    },
    {
      "brand": "Citadel",
      "name": "Skeleton Horde",
      "confidence": 0.9
    },
    {
      "brand": "Citadel",
      "name": "Karak",
      "confidence": 0.9
    },
    {
      "brand": "Citadel",
      "name": "Pallid Wych Flesh",
      "confidence": 0.9
    },
    {
      "brand": "Citadel",
      "name": "Skrag Brown",
      "confidence": 0.9
    },
    {
      "brand": "Citadel",
      "name": "Steel Legion",
      "confidence": 0.9
    },
    {
      "brand": "Citadel",
      "name": "Blood Angels Red",
      "confidence": 0.9
    },
    {
      "brand": "Citadel",
      "name": "Evil Sunz",
      "confidence": 0.9
    },
    {
      "brand": "Citadel",
      "name": "Wild Rider Red",
      "confidence": 0.9
    },
    {
      "brand": "Citadel",
      "name": "Sybarite Green",
      "confidence": 0.9
    },
    {
      "brand": "Citadel",
      "name": "Leadbelcher",
      "confidence": 0.9
    },
    {
      "brand": "Citadel",
      "name": "Stormhost Silver",
      "confidence": 0.9
    },
    {
      "brand": "Citadel",
      "name": "Agrax Earthshade",
      "confidence": 0.9
    },
    {
      "brand": "Citadel",
      "name": "Nazdreg Yellow",
      "confidence": 0.9
    },
    {
      "brand": "Citadel",
      "name": "Aggaros",
      "confidence": 0.9
    },
    {
      "brand": "Citadel",
      "name": "Flash Gitz Yellow",
      "confidence": 0.9
    },
    {
      "brand": "Citadel",
      "name": "Wraithbone",
      "confidence": 0.9
    },
    {
      "brand": "Citadel",
      "name": "Reikland Fleshshade",
      "confidence": 0.9
    },
    {
      "brand": "Citadel",
      "name": "Blood Angels",
      "confidence": 0.9
    },
    {
      "brand": "Army Painter",
      "name": "Army Painter Dark Tone",
      "confidence": 0.8
    }
  ],
  "steps": [],
  "images": [
    {
      "filename": "23968b501c52_1.png",
      "url": "https://d1w82usnq70pt2.cloudfront.net/wp-content/uploads/2023/12/Conquest-696x392.png",
      "alt_text": ""
    },
    {
      "filename": "23968b501c52_2.jpg",
      "url": "https://d1w82usnq70pt2.cloudfront.net/wp-content/uploads/2024/08/PXL_20240621_23064345221-1024x1024.jpg",
      "alt_text": ""
    },
    {
      "filename": "23968b501c52_4.jpg",
      "url": "https://d1w82usnq70pt2.cloudfront.net/wp-content/uploads/2024/06/efreet-1024x502.jpg",
      "alt_text": ""
    },
    {
      "filename": "23968b501c52_6.jpg",
      "url": "https://d1w82usnq70pt2.cloudfront.net/wp-content/uploads/2024/08/PXL_20240809_225203358.MP2_-1024x596.jpg",
      "alt_text": ""
    },
    {
      "filename": "23968b501c52_8.jpg",
      "url": "https://d1w82usnq70pt2.cloudfront.net/wp-content/uploads/2024/08/PXL_20240808_230850362.MP_-1024x360.jpg",
      "alt_text": ""
    },
    {
      "filename": "23968b501c52_10.jpg",
      "url": "https://d1w82usnq70pt2.cloudfront.net/wp-content/uploads/2024/08/PXL_20240816_232139870.MP2_-1024x638.jpg",
      "alt_text": ""
    },
    {
      "filename": "23968b501c52_12.jpg",
      "url": "https://d1w82usnq70pt2.cloudfront.net/wp-content/uploads/2024/08/PXL_20240819_2206387842-836x1024.jpg",
      "alt_text": ""
    },
    {
      "filename": "23968b501c52_14.jpg",
      "url": "https://d1w82usnq70pt2.cloudfront.net/wp-content/uploads/2024/08/PXL_20240812_110739101.MP_-1024x517.jpg",
      "alt_text": ""
    },
    {
      "filename": "23968b501c52_16.jpg",
      "url": "https://d1w82usnq70pt2.cloudfront.net/wp-content/uploads/2024/08/PXL_20240812_122703357.MP_-1024x566.jpg",
      "alt_text": ""
    },
    {
      "filename": "23968b501c52_18.jpg",
      "url": "https://d1w82usnq70pt2.cloudfront.net/wp-content/uploads/2024/08/PXL_20240823_221957490-1024x807.jpg",
      "alt_text": ""
    },
    {
      "filename": "23968b501c52_20.png",
      "url": "https://d1w82usnq70pt2.cloudfront.net/wp-content/uploads/2024/08/Screenshot-2024-08-26-153851.png",
      "alt_text": ""
    },
    {
      "filename": "23968b501c52_22.jpg",
      "url": "https://d1w82usnq70pt2.cloudfront.net/wp-content/uploads/2024/08/PXL_20240826_2027475082-1024x1024.jpg",
      "alt_text": ""
    },
    {
      "filename": "23968b501c52_24.jpg",
      "url": "https://d1w82usnq70pt2.cloudfront.net/wp-content/uploads/2024/08/PXL_20240826_2015142412-1024x1024.jpg",
      "alt_text": ""
    },
    {
      "filename": "23968b501c52_26.jpg",
      "url": "https://d1w82usnq70pt2.cloudfront.net/wp-content/uploads/2024/08/PXL_20240826_2014170212-1024x1024.jpg",
      "alt_text": ""
    },
    {
      "filename": "23968b501c52_28.jpg",
      "url": "https://d1w82usnq70pt2.cloudfront.net/wp-content/uploads/2024/08/PXL_20240826_2013490312-1024x1024.jpg",
      "alt_text": ""
    },
    {
      "filename": "23968b501c52_30.jpg",
      "url": "https://d1w82usnq70pt2.cloudfront.net/wp-content/uploads/2024/08/PXL_20240825_1952091512-1024x441.jpg",
      "alt_text": ""
    },
    {
      "filename": "23968b501c52_32.jpg",
      "url": "https://d1w82usnq70pt2.cloudfront.net/wp-content/uploads/2024/08/PXL_20240826_2011573902-1024x794.jpg",
      "alt_text": ""
    },
    {
      "filename": "23968b501c52_34.jpg",
      "url": "https://d1w82usnq70pt2.cloudfront.net/wp-content/uploads/2024/08/PXL_20240621_23064345221-1024x1024.jpg",
      "alt_text": ""
    },
    {
      "filename": "23968b501c52_36.jpg",
      "url": "https://d1w82usnq70pt2.cloudfront.net/wp-content/uploads/2024/08/PXL_20240826_2034031312-1024x562.jpg",
      "alt_text": ""
    },
    {
      "filename": "23968b501c52_38.jpg",
      "url": "https://d1w82usnq70pt2.cloudfront.net/wp-content/uploads/2024/08/PXL_20240826_2035307312-1024x509.jpg",
      "alt_text": ""
    },
    {
      "filename": "23968b501c52_40.jpg",
      "url": "https://d1w82usnq70pt2.cloudfront.net/wp-content/uploads/2024/08/PXL_20240826_2036594102-1024x542.jpg",
      "alt_text": ""
    },
    {
      "filename": "23968b501c52_42.jpg",
      "url": "https://d1w82usnq70pt2.cloudfront.net/wp-content/uploads/2024/08/PXL_20240826_2039060162-1024x598.jpg",
      "alt_text": ""
    }
  ],
  "scraped_at": "2026-02-01T20:51:30.191834",
  "has_ground_truth": true
}